lookup.py
lookup-0.2.dist-info/DESCRIPTION.rst
lookup-0.2.dist-info/entry_points.txt
lookup-0.2.dist-info/METADATA
lookup-0.2.dist-info/metadata.json
lookup-0.2.dist-info/RECORD
lookup-0.2.dist-info/top_level.txt
lookup-0.2.dist-info/WHEEL
