Metadata-Version: 1.1
Name: lookup
Version: 0.2
Summary: Dictionary via the command line
Home-page: https://github.com/fengsp/lookup
Author: Shipeng Feng
Author-email: fsp261@gmail.com
License: BSD
Platform: any
Classifier: Environment :: Console
Classifier: Intended Audience :: Developers
Classifier: License :: OSI Approved :: BSD License
Classifier: Operating System :: OS Independent
Classifier: Programming Language :: Python
